Metadata-Version: 2.4
Name: mcp-browser-use
Version: 0.1.5
Summary: MCP server for browser-use
Author-email: Vinayak Mehta <vmehta94@gmail.com>
License: Apache-2.0
Project-URL: Homepage, https://github.com/vinayak-mehta/mcp-browser-use
Project-URL: Bug Tracker, https://github.com/vinayak-mehta/mcp-browser-use/issues
Classifier: Programming Language :: Python :: 3
Classifier: Programming Language :: Python :: 3.11
Classifier: Programming Language :: Python :: 3.12
Classifier: Programming Language :: Python :: 3.13
Classifier: License :: OSI Approved :: Apache Software License
Requires-Python: >=3.10
License-File: LICENSE
Requires-Dist: mcp>=0.1.0
Requires-Dist: python-dotenv>=1.0.0
Requires-Dist: fastapi>=0.109.0
Requires-Dist: uvicorn>=0.27.0
Requires-Dist: playwright>=1.50.0
Requires-Dist: browser-use>=0.1.40
Dynamic: license-file
